Podd-0.1.19.data/data/podd/templates/_podcast.html
Podd-0.1.19.data/data/podd/templates/base.html
Podd-0.1.19.data/data/podd/templates/base.txt
podd/__init__.py
podd/__main__.py
podd/cli.py
podd/database.py
podd/downloader.py
podd/logger.py
podd/message.py
podd/podcast.py
podd/settings.py
podd/utilities.py
podd/templates/_podcast.html
podd/templates/base.html
podd/templates/base.txt
tests/__init__.py
tests/test_database.py
tests/test_logger.py
tests/test_regex.py
tests/utilities.py
Podd-0.1.19.dist-info/LICENSE.txt
Podd-0.1.19.dist-info/METADATA
Podd-0.1.19.dist-info/WHEEL
Podd-0.1.19.dist-info/entry_points.txt
Podd-0.1.19.dist-info/top_level.txt
Podd-0.1.19.dist-info/RECORD
