Metadata-Version: 2.1
Name: Podd
Version: 0.1.19
Summary: A Podcast downloader
Home-page: https://github.com/jakkso/Podd
Author: Alexander Potts
Author-email: alexander.potts@gmail.com
License: UNKNOWN
Platform: UNKNOWN
Classifier: Development Status :: 4 - Beta
Classifier: Programming Language :: Python :: 3.6
Classifier: License :: OSI Approved :: GNU General Public License v2 (GPLv2)
Classifier: Operating System :: MacOS
Classifier: Operating System :: POSIX :: Linux
Requires-Dist: feedparser
Requires-Dist: jinja2
Requires-Dist: mutagen
Requires-Dist: click
Requires-Dist: keyring
Requires-Dist: requests
